MANIFEST.in
README.txt
setup.cfg
setup.py
yxspkg_tecfile.py
yxspkg_tecfile.egg-info/PKG-INFO
yxspkg_tecfile.egg-info/SOURCES.txt
yxspkg_tecfile.egg-info/dependency_links.txt
yxspkg_tecfile.egg-info/top_level.txt