Metadata-Version: 1.1
Name: yxspkg-tecfile
Version: 1.4
Summary: A simple API to prase some CFD data file such as ".prof(fluent)", ".txt" etc.
Home-page: https://github.com/blacksong
Author: Blacksong
Author-email: blacksong@yeah.net
License: UNKNOWN
Platform: any
Classifier: Programming Language :: Python :: 3
Classifier: Operating System :: OS Independent
Classifier: Topic :: Software Development :: Libraries :: Python Modules
